README.md
setup.cfg
setup.py
InsolvencyAnnouncementsGer/InsolvencyAnnouncementsGer.py
InsolvencyAnnouncementsGer/InsolvencyAnnouncementsGer_summaries.py
InsolvencyAnnouncementsGer/__init__.py
InsolvencyAnnouncementsGer.egg-info/PKG-INFO
InsolvencyAnnouncementsGer.egg-info/SOURCES.txt
InsolvencyAnnouncementsGer.egg-info/dependency_links.txt
InsolvencyAnnouncementsGer.egg-info/requires.txt
InsolvencyAnnouncementsGer.egg-info/top_level.txt
InsolvencyAnnouncementsGer.egg-info/.ipynb_checkpoints/PKG-INFO-checkpoint
InsolvencyAnnouncementsGer.egg-info/.ipynb_checkpoints/SOURCES-checkpoint.txt
InsolvencyAnnouncementsGer.egg-info/.ipynb_checkpoints/dependency_links-checkpoint.txt