Metadata-Version: 2.1
Name: InsolvencyAnnouncementsGer
Version: 0.2.1
Summary: InsolvencyAnnouncementsGer is a Python library for searching, viewing and scraping public announcements of German bankruptcy courts from https://www.insolvenzbekanntmachungen.de
Home-page: https://github.com/NDelventhal/InsolvencyAnnouncementsGer
Author: Niall Delventhal
Author-email: ni.delventhal@gmail.com
License: MIT
Download-URL: https://github.com/NDelventhal/InsolvencyAnnouncementsGer/archive/v_021.tar.gz
Platform: UNKNOWN
Classifier: Intended Audience :: Science/Research
Classifier: License :: OSI Approved :: MIT License
Classifier: Development Status :: 3 - Alpha
Classifier: Programming Language :: Python :: 3.7
